tsfeatures/__init__.py
tsfeatures/compare_with_r.py
tsfeatures/m4_data.py
tsfeatures/tsfeatures.py
tsfeatures/tsfeatures_r.py
tsfeatures/utils.py
tsfeatures/metrics/__init__.py
tsfeatures/metrics/metrics.py
tsfeatures/tests/__init__.py
tsfeatures/tests/test_acf_features.py
tsfeatures/tests/test_arch_stat.py
tsfeatures/tests/test_holt_parameters.py
tsfeatures/tests/test_mutability.py
tsfeatures/tests/test_pacf_features.py
tsfeatures/tests/test_pipeline.py
tsfeatures/tests/test_small_ts.py
tsfeatures/tests/test_sparsity.py
tsfeatures/tests/test_statistics.py
tsfeatures-0.4.5.dist-info/LICENSE
tsfeatures-0.4.5.dist-info/METADATA
tsfeatures-0.4.5.dist-info/WHEEL
tsfeatures-0.4.5.dist-info/top_level.txt
tsfeatures-0.4.5.dist-info/RECORD
