Metadata-Version: 2.1
Name: tsfeatures
Version: 0.4.5
Summary: Calculates various features from time series data.
Home-page: https://github.com/Nixtla/tsfeatures
Classifier: Programming Language :: Python :: 3
Classifier: License :: OSI Approved :: MIT License
Classifier: Operating System :: OS Independent
Requires-Python: >=3.7
License-File: LICENSE
Requires-Dist: antropy (>=0.1.4)
Requires-Dist: arch (>=4.11)
Requires-Dist: pandas (>=1.0.5)
Requires-Dist: scikit-learn (>=0.23.1)
Requires-Dist: statsmodels (>=0.13.2)
Requires-Dist: supersmoother (>=0.4)
